[
  {
    "line": 2,
    "elements": [
      {
        "line": 4,
        "name": "",
        "description": "",
        "type": "background",
        "keyword": "Background",
        "steps": [
          {
            "result": {
              "duration": 13865235200,
              "status": "passed"
            },
            "line": 5,
            "name": "Cargar la pagina de TLCNp",
            "match": {
              "location": "tlcnpStepDefinition.cargar_la_pagina_de_TLCNp()"
            },
            "keyword": "Given "
          }
        ]
      },
      {
        "line": 19,
        "name": "Transferencia a cuentas propias BCP",
        "description": "",
        "id": "transferencias-entre-cuentas;transferencia-a-cuentas-propias-bcp;;2",
        "type": "scenario",
        "keyword": "Scenario Outline",
        "steps": [
          {
            "result": {
              "duration": 909271200,
              "status": "passed"
            },
            "line": 9,
            "name": "selecciono tipo de tarjeta \"Acceso Empresarial\"",
            "match": {
              "arguments": [
                {
                  "val": "Acceso Empresarial",
                  "offset": 28
                }
              ],
              "location": "tlcnpStepDefinition.selecciono_tipo_tarjeta(String)"
            },
            "keyword": "When "
          },
          {
            "result": {
              "duration": 6241270100,
              "status": "passed"
            },
            "line": 10,
            "name": "Ingreso tarjeta \"5001207417\" con \"111111\"",
            "match": {
              "arguments": [
                {
                  "val": "5001207417",
                  "offset": 17
                },
                {
                  "val": "111111",
                  "offset": 34
                }
              ],
              "location": "tlcnpStepDefinition.escribitar_Tarjeta(String,String)"
            },
            "keyword": "And "
          },
          {
            "result": {
              "duration": 3382759100,
              "status": "passed"
            },
            "line": 11,
            "name": "doy clic a transferencias BCP con cuentas propias",
            "match": {
              "location": "tlcnpStepDefinition.clic_trasnferenciasPropiasbcp()"
            },
            "keyword": "And "
          },
          {
            "result": {
              "duration": 2078370600,
              "status": "passed"
            },
            "line": 12,
            "name": "selecciono el numero de cuenta \"193-1550736-1-08\"",
            "match": {
              "arguments": [
                {
                  "val": "193-1550736-1-08",
                  "offset": 32
                }
              ],
              "location": "tlcnpStepDefinition.selecciono_numero_cuenta(String)"
            },
            "keyword": "And "
          },
          {
            "result": {
              "duration": 5028600,
              "status": "passed"
            },
            "line": 13,
            "name": "selecciono datos de la cuenta abono \"193-1550736-1-08\" con la misma moneda \"true\" con cuesta destino \"193-1551734-0-79\"",
            "match": {
              "arguments": [
                {
                  "val": "193-1550736-1-08",
                  "offset": 37
                },
                {
                  "val": "true",
                  "offset": 76
                },
                {
                  "val": "193-1551734-0-79",
                  "offset": 102
                }
              ],
              "location": "tlcnpStepDefinition.selecciono_datos_cuenta_destino(String,Boolean,String)"
            },
            "keyword": "And "
          },
          {
            "result": {
              "duration": 10089233400,
              "status": "passed"
            },
            "line": 14,
            "name": "selecciono datos de la cuenta destino \"193-1551734-0-79\" con \"10\" con moneda en \"US$\"",
            "match": {
              "arguments": [
                {
                  "val": "193-1551734-0-79",
                  "offset": 39
                },
                {
                  "val": "10",
                  "offset": 62
                },
                {
                  "val": "US$",
                  "offset": 81
                }
              ],
              "location": "tlcnpStepDefinition.selecciono_datos_cuenta_destino(String,String,String)"
            },
            "keyword": "And "
          },
          {
            "result": {
              "duration": 2972762900,
              "status": "passed"
            },
            "line": 15,
            "name": "envio a firma \"Enviar a firma\"",
            "match": {
              "arguments": [
                {
                  "val": "Enviar a firma",
                  "offset": 15
                }
              ],
              "location": "tlcnpStepDefinition.envio_firma(String)"
            },
            "keyword": "And "
          },
          {
            "result": {
              "duration": 341151100,
              "status": "passed"
            },
            "line": 16,
            "name": "Guardar numero de operacion \"5001207417\" con \"10\"",
            "match": {
              "arguments": [
                {
                  "val": "5001207417",
                  "offset": 29
                },
                {
                  "val": "10",
                  "offset": 46
                }
              ],
              "location": "tlcnpStepDefinition.guardar_num_operacion(String,String)"
            },
            "keyword": "And "
          }
        ],
        "tags": [
          {
            "name": "@tlcnp"
          },
          {
            "name": "@tlcnp1"
          }
        ]
      }
    ],
    "name": "Transferencias entre cuentas",
    "description": "",
    "id": "transferencias-entre-cuentas",
    "keyword": "Feature",
    "uri": "src/test/resources/features/web/tlcnp.feature",
    "tags": [
      {
        "name": "@tlcnp",
        "type": "Tag",
        "location": {
          "line": 1,
          "column": 1
        }
      }
    ]
  }
]